CHANGES.txt
LICENSE.txt
MANIFEST.in
README.txt
bootstrap.py
buildout.cfg
setup.py
src/j01/__init__.py
src/j01.pager.egg-info/PKG-INFO
src/j01.pager.egg-info/SOURCES.txt
src/j01.pager.egg-info/dependency_links.txt
src/j01.pager.egg-info/namespace_packages.txt
src/j01.pager.egg-info/not-zip-safe
src/j01.pager.egg-info/requires.txt
src/j01.pager.egg-info/top_level.txt
src/j01/pager/README.txt
src/j01/pager/README_MIGRATION_P2P3.py
src/j01/pager/__init__.py
src/j01/pager/batch.py
src/j01/pager/browser.py
src/j01/pager/configure.zcml
src/j01/pager/interfaces.py
src/j01/pager/jsonrpc.py
src/j01/pager/tests.py
src/j01/pager/traverser.py
src/j01/pager/traverser.zcml
src/j01/pager/css/j01.pager.css
src/j01/pager/js/j01.pager.js
src/j01/pager/less/.xpp
src/j01/pager/less/j01.pager.less
src/j01/pager/less/variables.less