Metadata-Version: 2.1
Name: j01.pager
Version: 1.0.0
Summary: JQuery and j01.jsonrpc based pagination for Zope 3
Home-page: http://pypi.python.org/pypi/j01.pager
Author: Roger Ineichen, Projekt01 GmbH
Author-email: dev@projekt01.ch
License: ZPL 2.1
Keywords: J01 XHR ajax z3c pagination JSON-RPC JQuery Zope3
Platform: UNKNOWN
Classifier: Development Status :: 5 - Production/Stable
Classifier: Environment :: Web Environment
Classifier: Intended Audience :: Developers
Classifier: License :: OSI Approved :: Zope Public License
Classifier: Programming Language :: Python
Classifier: Natural Language :: English
Classifier: Operating System :: OS Independent
Classifier: Topic :: Internet :: WWW/HTTP
Classifier: Framework :: Zope3
Provides-Extra: test
